[1,0,0,[["cc.Mesh",["_native","_hash","_struct"],1,11]],[[0,0,1,2,3]],[[0,".bin",820819198,[{"primitives":[{"primitiveMode":7,"vertexBundelIndices":[0],"indexView":{"offset":21600,"length":1440,"count":720,"stride":2}}],"vertexBundles":[{"view":{"offset":0,"length":21600,"count":300,"stride":72},"attributes":[{"name":"a_position","format":32,"isNormalized":false},{"name":"a_normal","format":32,"isNormalized":false},{"name":"a_texCoord","format":21,"isNormalized":false},{"name":"a_tangent","format":44,"isNormalized":false},{"name":"a_joints","format":42,"isNormalized":false},{"name":"a_weights","format":44,"isNormalized":false}]}]},"minPosition",8,[1,-0.3358529210090637,0.4797073006629944,0.3802853524684906],"maxPosition",8,[1,0.33585360646247864,0.6921791434288025,0.527127742767334]]],-1],0,0,[],[],[]]
